build/lib/build/lib/pysymbolcheck/__init__.py
build/lib/build/lib/pysymbolcheck/__main__.py
build/lib/pysymbolcheck/__init__.py
build/lib/pysymbolcheck/__main__.py
pysymbolcheck/__init__.py
pysymbolcheck/__main__.py
pysymbolcheck/basic_rules.json
pysymbolcheck-2.12.0.dist-info/licenses/LICENSE
pysymbolcheck-2.12.0.dist-info/METADATA
pysymbolcheck-2.12.0.dist-info/WHEEL
pysymbolcheck-2.12.0.dist-info/entry_points.txt
pysymbolcheck-2.12.0.dist-info/top_level.txt
pysymbolcheck-2.12.0.dist-info/RECORD
