Metadata-Version: 2.4
Name: pysymbolcheck
Version: 2.12.0
Summary: ELF symbol check
Maintainer-email: Konrad Weihmann <kweihmann@outlook.com>
License-Expression: BSD-2-Clause
Project-URL: homepage, https://github.com/priv-kweihmann/pysymbolcheck
Project-URL: repository, https://github.com/priv-kweihmann/pysymbolcheck.git
Project-URL: bugtracker, https://github.com/priv-kweihmann/pysymbolcheck/issues
Classifier: Development Status :: 4 - Beta
Classifier: Environment :: Console
Classifier: Intended Audience :: Developers
Classifier: Natural Language :: English
Classifier: Operating System :: POSIX :: Linux
Classifier: Programming Language :: Python :: 3 :: Only
Classifier: Programming Language :: Python :: 3
Classifier: Programming Language :: Python :: 3.10
Classifier: Programming Language :: Python :: 3.11
Classifier: Programming Language :: Python :: 3.12
Classifier: Programming Language :: Python :: 3.13
Classifier: Programming Language :: Python :: 3.14
Requires-Python: >=3.10
License-File: LICENSE
Requires-Dist: jsonmerge~=1.9
Requires-Dist: pyelftools==0.32
Provides-Extra: dev
Requires-Dist: Flake8-pyproject==1.2.3; extra == "dev"
Requires-Dist: bump-my-version==1.2.4; extra == "dev"
Requires-Dist: build==1.3.0; extra == "dev"
Requires-Dist: dlint==0.16.0; extra == "dev"
Requires-Dist: flake8==7.3.0; extra == "dev"
Requires-Dist: flake8-2020==1.8.1; extra == "dev"
Requires-Dist: flake8-broken-line==1.0.0; extra == "dev"
Requires-Dist: flake8-bugbear==24.12.12; extra == "dev"
Requires-Dist: flake8-builtins==3.0.0; extra == "dev"
Requires-Dist: flake8-coding==1.3.2; extra == "dev"
Requires-Dist: flake8-commas==4.0.0; extra == "dev"
Requires-Dist: flake8-comprehensions==3.17.0; extra == "dev"
Requires-Dist: flake8-debugger==4.1.2; extra == "dev"
Requires-Dist: flake8-docstrings==1.7.0; extra == "dev"
Requires-Dist: flake8-eradicate==1.5.0; extra == "dev"
Requires-Dist: flake8-executable==2.1.3; extra == "dev"
Requires-Dist: flake8-fixme==1.1.1; extra == "dev"
Requires-Dist: flake8-isort==6.1.2; extra == "dev"
Requires-Dist: flake8-mutable==1.2.0; extra == "dev"
Requires-Dist: flake8-pep3101==2.1.0; extra == "dev"
Requires-Dist: flake8-print==5.0.0; extra == "dev"
Requires-Dist: flake8-quotes==3.4.0; extra == "dev"
Requires-Dist: flake8-requirements==2.3.0; extra == "dev"
Requires-Dist: flake8-variables-names==0.0.6; extra == "dev"
Requires-Dist: twine==6.2.0; extra == "dev"
Requires-Dist: wheel~=0.45; extra == "dev"
Dynamic: license-file
